{"nodes": [{"id": "users_quentin_gallois_documents_projects_perso_klozy_klozy_mobile_lib_src_feature_auth_presentation_bloc_auth_bloc_dart", "label": "auth_bloc.dart", "file_type": "code", "source_file": "lib/src/feature/auth/presentation/bloc/auth_bloc.dart", "source_location": null}, {"id": "bloc_auth_bloc_authbloc", "label": "AuthBloc", "file_type": "code", "source_file": "lib/src/feature/auth/presentation/bloc/auth_bloc.dart", "source_location": null}, {"id": "bloc", "label": "Bloc", "file_type": "code", "source_file": null, "source_location": null}, {"id": "authevent", "label": "AuthEvent", "file_type": "code", "source_file": null, "source_location": null}, {"id": "authstate", "label": "AuthState", "file_type": "code", "source_file": null, "source_location": null}, {"id": "authemailsubmitted", "label": "AuthEmailSubmitted", "file_type": "code", "source_file": null, "source_location": null}, {"id": "authgooglepressed", "label": "AuthGooglePressed", "file_type": "code", "source_file": null, "source_location": null}, {"id": "authapplepressed", "label": "AuthApplePressed", "file_type": "code", "source_file": null, "source_location": null}, {"id": "authpasswordresetrequested", "label": "AuthPasswordResetRequested", "file_type": "code", "source_file": null, "source_location": null}, {"id": "authphonestarted", "label": "AuthPhoneStarted", "file_type": "code", "source_file": null, "source_location": null}, {"id": "authphonecodesubmitted", "label": "AuthPhoneCodeSubmitted", "file_type": "code", "source_file": null, "source_location": null}, {"id": "authpasswordresetsent", "label": "AuthPasswordResetSent", "file_type": "code", "source_file": null, "source_location": null}, {"id": "authcodesent", "label": "AuthCodeSent", "file_type": "code", "source_file": null, "source_location": null}, {"id": "authsuccess", "label": "AuthSuccess", "file_type": "code", "source_file": null, "source_location": null}, {"id": "authloading", "label": "AuthLoading", "file_type": "code", "source_file": null, "source_location": null}, {"id": "authfailure", "label": "AuthFailure", "file_type": "code", "source_file": null, "source_location": null}, {"id": "annotation_injectable", "label": "@injectable", "file_type": "concept", "source_file": null, "source_location": null}, {"id": "bloc_auth_bloc_authrepository", "label": "_authRepository", "file_type": "code", "source_file": "lib/src/feature/auth/presentation/bloc/auth_bloc.dart", "source_location": null}, {"id": "authrepository", "label": "AuthRepository", "file_type": "code", "source_file": null, "source_location": null}, {"id": "bloc_auth_bloc_merepository", "label": "_meRepository", "file_type": "code", "source_file": "lib/src/feature/auth/presentation/bloc/auth_bloc.dart", "source_location": null}, {"id": "merepository", "label": "MeRepository", "file_type": "code", "source_file": null, "source_location": null}, {"id": "bloc_auth_bloc_onemail", "label": "_onEmail", "file_type": "code", "source_file": "lib/src/feature/auth/presentation/bloc/auth_bloc.dart", "source_location": null}, {"id": "bloc_auth_bloc_ongoogle", "label": "_onGoogle", "file_type": "code", "source_file": "lib/src/feature/auth/presentation/bloc/auth_bloc.dart", "source_location": null}, {"id": "bloc_auth_bloc_onapple", "label": "_onApple", "file_type": "code", "source_file": "lib/src/feature/auth/presentation/bloc/auth_bloc.dart", "source_location": null}, {"id": "bloc_auth_bloc_onpasswordreset", "label": "_onPasswordReset", "file_type": "code", "source_file": "lib/src/feature/auth/presentation/bloc/auth_bloc.dart", "source_location": null}, {"id": "bloc_auth_bloc_onphonestarted", "label": "_onPhoneStarted", "file_type": "code", "source_file": "lib/src/feature/auth/presentation/bloc/auth_bloc.dart", "source_location": null}, {"id": "bloc_auth_bloc_onphonecode", "label": "_onPhoneCode", "file_type": "code", "source_file": "lib/src/feature/auth/presentation/bloc/auth_bloc.dart", "source_location": null}, {"id": "bloc_auth_bloc_finishauth", "label": "_finishAuth", "file_type": "code", "source_file": "lib/src/feature/auth/presentation/bloc/auth_bloc.dart", "source_location": null}, {"id": "bloc_auth_bloc_guard", "label": "_guard", "file_type": "code", "source_file": "lib/src/feature/auth/presentation/bloc/auth_bloc.dart", "source_location": null}, {"id": "package_bloc_bloc_dart", "label": "package:bloc/bloc.dart", "file_type": "code", "source_file": null, "source_location": null}, {"id": "package_injectable_injectable_dart", "label": "package:injectable/injectable.dart", "file_type": "code", "source_file": null, "source_location": null}, {"id": "package_klozy_src_domain_auth_auth_exception_dart", "label": "package:klozy/src/domain/auth/auth_exception.dart", "file_type": "code", "source_file": null, "source_location": null}, {"id": "package_klozy_src_domain_auth_auth_repository_dart", "label": "package:klozy/src/domain/auth/auth_repository.dart", "file_type": "code", "source_file": null, "source_location": null}, {"id": "package_klozy_src_domain_auth_entity_auth_user_dart", "label": "package:klozy/src/domain/auth/entity/auth_user.dart", "file_type": "code", "source_file": null, "source_location": null}, {"id": "package_klozy_src_domain_me_me_repository_dart", "label": "package:klozy/src/domain/me/me_repository.dart", "file_type": "code", "source_file": null, "source_location": null}, {"id": "package_klozy_src_feature_auth_presentation_bloc_auth_event_dart", "label": "package:klozy/src/feature/auth/presentation/bloc/auth_event.dart", "file_type": "code", "source_file": null, "source_location": null}, {"id": "package_klozy_src_feature_auth_presentation_bloc_auth_state_dart", "label": "package:klozy/src/feature/auth/presentation/bloc/auth_state.dart", "file_type": "code", "source_file": null, "source_location": null}], "edges": [{"source": "users_quentin_gallois_documents_projects_perso_klozy_klozy_mobile_lib_src_feature_auth_presentation_bloc_auth_bloc_dart", "target": "bloc_auth_bloc_authbloc", "relation": "defines", "confidence": "EXTRACTED", "confidence_score": 1.0, "source_file": "lib/src/feature/auth/presentation/bloc/auth_bloc.dart", "source_location": null, "weight": 1.0}, {"source": "bloc_auth_bloc_authbloc", "target": "bloc", "relation": "inherits", "confidence": "EXTRACTED", "confidence_score": 1.0, "source_file": "lib/src/feature/auth/presentation/bloc/auth_bloc.dart", "source_location": null, "weight": 1.0}, {"source": "bloc_auth_bloc_authbloc", "target": "authevent", "relation": "references", "confidence": "EXTRACTED", "confidence_score": 1.0, "source_file": "lib/src/feature/auth/presentation/bloc/auth_bloc.dart", "source_location": null, "weight": 1.0}, {"source": "bloc_auth_bloc_authbloc", "target": "authstate", "relation": "references", "confidence": "EXTRACTED", "confidence_score": 1.0, "source_file": "lib/src/feature/auth/presentation/bloc/auth_bloc.dart", "source_location": null, "weight": 1.0}, {"source": "bloc_auth_bloc_authbloc", "target": "authemailsubmitted", "relation": "calls", "confidence": "EXTRACTED", "confidence_score": 1.0, "source_file": "lib/src/feature/auth/presentation/bloc/auth_bloc.dart", "source_location": null, "weight": 1.0, "context": "bloc_event"}, {"source": "bloc_auth_bloc_authbloc", "target": "authgooglepressed", "relation": "calls", "confidence": "EXTRACTED", "confidence_score": 1.0, "source_file": "lib/src/feature/auth/presentation/bloc/auth_bloc.dart", "source_location": null, "weight": 1.0, "context": "bloc_event"}, {"source": "bloc_auth_bloc_authbloc", "target": "authapplepressed", "relation": "calls", "confidence": "EXTRACTED", "confidence_score": 1.0, "source_file": "lib/src/feature/auth/presentation/bloc/auth_bloc.dart", "source_location": null, "weight": 1.0, "context": "bloc_event"}, {"source": "bloc_auth_bloc_authbloc", "target": "authpasswordresetrequested", "relation": "calls", "confidence": "EXTRACTED", "confidence_score": 1.0, "source_file": "lib/src/feature/auth/presentation/bloc/auth_bloc.dart", "source_location": null, "weight": 1.0, "context": "bloc_event"}, {"source": "bloc_auth_bloc_authbloc", "target": "authphonestarted", "relation": "calls", "confidence": "EXTRACTED", "confidence_score": 1.0, "source_file": "lib/src/feature/auth/presentation/bloc/auth_bloc.dart", "source_location": null, "weight": 1.0, "context": "bloc_event"}, {"source": "bloc_auth_bloc_authbloc", "target": "authphonecodesubmitted", "relation": "calls", "confidence": "EXTRACTED", "confidence_score": 1.0, "source_file": "lib/src/feature/auth/presentation/bloc/auth_bloc.dart", "source_location": null, "weight": 1.0, "context": "bloc_event"}, {"source": "bloc_auth_bloc_authbloc", "target": "authpasswordresetsent", "relation": "calls", "confidence": "EXTRACTED", "confidence_score": 1.0, "source_file": "lib/src/feature/auth/presentation/bloc/auth_bloc.dart", "source_location": null, "weight": 1.0, "context": "emit_state"}, {"source": "bloc_auth_bloc_authbloc", "target": "authcodesent", "relation": "calls", "confidence": "EXTRACTED", "confidence_score": 1.0, "source_file": "lib/src/feature/auth/presentation/bloc/auth_bloc.dart", "source_location": null, "weight": 1.0, "context": "emit_state"}, {"source": "bloc_auth_bloc_authbloc", "target": "authsuccess", "relation": "calls", "confidence": "EXTRACTED", "confidence_score": 1.0, "source_file": "lib/src/feature/auth/presentation/bloc/auth_bloc.dart", "source_location": null, "weight": 1.0, "context": "emit_state"}, {"source": "bloc_auth_bloc_authbloc", "target": "authloading", "relation": "calls", "confidence": "EXTRACTED", "confidence_score": 1.0, "source_file": "lib/src/feature/auth/presentation/bloc/auth_bloc.dart", "source_location": null, "weight": 1.0, "context": "emit_state"}, {"source": "bloc_auth_bloc_authbloc", "target": "authfailure", "relation": "calls", "confidence": "EXTRACTED", "confidence_score": 1.0, "source_file": "lib/src/feature/auth/presentation/bloc/auth_bloc.dart", "source_location": null, "weight": 1.0, "context": "emit_state"}, {"source": "bloc_auth_bloc_authbloc", "target": "authfailure", "relation": "calls", "confidence": "EXTRACTED", "confidence_score": 1.0, "source_file": "lib/src/feature/auth/presentation/bloc/auth_bloc.dart", "source_location": null, "weight": 1.0, "context": "emit_state"}, {"source": "bloc_auth_bloc_authbloc", "target": "annotation_injectable", "relation": "configures", "confidence": "EXTRACTED", "confidence_score": 1.0, "source_file": "lib/src/feature/auth/presentation/bloc/auth_bloc.dart", "source_location": null, "weight": 1.0}, {"source": "users_quentin_gallois_documents_projects_perso_klozy_klozy_mobile_lib_src_feature_auth_presentation_bloc_auth_bloc_dart", "target": "bloc_auth_bloc_authrepository", "relation": "defines", "confidence": "EXTRACTED", "confidence_score": 1.0, "source_file": "lib/src/feature/auth/presentation/bloc/auth_bloc.dart", "source_location": null, "weight": 1.0}, {"source": "users_quentin_gallois_documents_projects_perso_klozy_klozy_mobile_lib_src_feature_auth_presentation_bloc_auth_bloc_dart", "target": "authrepository", "relation": "references", "confidence": "EXTRACTED", "confidence_score": 1.0, "source_file": "lib/src/feature/auth/presentation/bloc/auth_bloc.dart", "source_location": null, "weight": 1.0, "context": "variable_type"}, {"source": "users_quentin_gallois_documents_projects_perso_klozy_klozy_mobile_lib_src_feature_auth_presentation_bloc_auth_bloc_dart", "target": "bloc_auth_bloc_merepository", "relation": "defines", "confidence": "EXTRACTED", "confidence_score": 1.0, "source_file": "lib/src/feature/auth/presentation/bloc/auth_bloc.dart", "source_location": null, "weight": 1.0}, {"source": "users_quentin_gallois_documents_projects_perso_klozy_klozy_mobile_lib_src_feature_auth_presentation_bloc_auth_bloc_dart", "target": "merepository", "relation": "references", "confidence": "EXTRACTED", "confidence_score": 1.0, "source_file": "lib/src/feature/auth/presentation/bloc/auth_bloc.dart", "source_location": null, "weight": 1.0, "context": "variable_type"}, {"source": "users_quentin_gallois_documents_projects_perso_klozy_klozy_mobile_lib_src_feature_auth_presentation_bloc_auth_bloc_dart", "target": "bloc_auth_bloc_onemail", "relation": "defines", "confidence": "EXTRACTED", "confidence_score": 1.0, "source_file": "lib/src/feature/auth/presentation/bloc/auth_bloc.dart", "source_location": null, "weight": 1.0}, {"source": "users_quentin_gallois_documents_projects_perso_klozy_klozy_mobile_lib_src_feature_auth_presentation_bloc_auth_bloc_dart", "target": "bloc_auth_bloc_ongoogle", "relation": "defines", "confidence": "EXTRACTED", "confidence_score": 1.0, "source_file": "lib/src/feature/auth/presentation/bloc/auth_bloc.dart", "source_location": null, "weight": 1.0}, {"source": "users_quentin_gallois_documents_projects_perso_klozy_klozy_mobile_lib_src_feature_auth_presentation_bloc_auth_bloc_dart", "target": "bloc_auth_bloc_onapple", "relation": "defines", "confidence": "EXTRACTED", "confidence_score": 1.0, "source_file": "lib/src/feature/auth/presentation/bloc/auth_bloc.dart", "source_location": null, "weight": 1.0}, {"source": "users_quentin_gallois_documents_projects_perso_klozy_klozy_mobile_lib_src_feature_auth_presentation_bloc_auth_bloc_dart", "target": "bloc_auth_bloc_onpasswordreset", "relation": "defines", "confidence": "EXTRACTED", "confidence_score": 1.0, "source_file": "lib/src/feature/auth/presentation/bloc/auth_bloc.dart", "source_location": null, "weight": 1.0}, {"source": "users_quentin_gallois_documents_projects_perso_klozy_klozy_mobile_lib_src_feature_auth_presentation_bloc_auth_bloc_dart", "target": "bloc_auth_bloc_onphonestarted", "relation": "defines", "confidence": "EXTRACTED", "confidence_score": 1.0, "source_file": "lib/src/feature/auth/presentation/bloc/auth_bloc.dart", "source_location": null, "weight": 1.0}, {"source": "users_quentin_gallois_documents_projects_perso_klozy_klozy_mobile_lib_src_feature_auth_presentation_bloc_auth_bloc_dart", "target": "bloc_auth_bloc_onphonecode", "relation": "defines", "confidence": "EXTRACTED", "confidence_score": 1.0, "source_file": "lib/src/feature/auth/presentation/bloc/auth_bloc.dart", "source_location": null, "weight": 1.0}, {"source": "users_quentin_gallois_documents_projects_perso_klozy_klozy_mobile_lib_src_feature_auth_presentation_bloc_auth_bloc_dart", "target": "bloc_auth_bloc_finishauth", "relation": "defines", "confidence": "EXTRACTED", "confidence_score": 1.0, "source_file": "lib/src/feature/auth/presentation/bloc/auth_bloc.dart", "source_location": null, "weight": 1.0}, {"source": "users_quentin_gallois_documents_projects_perso_klozy_klozy_mobile_lib_src_feature_auth_presentation_bloc_auth_bloc_dart", "target": "bloc_auth_bloc_guard", "relation": "defines", "confidence": "EXTRACTED", "confidence_score": 1.0, "source_file": "lib/src/feature/auth/presentation/bloc/auth_bloc.dart", "source_location": null, "weight": 1.0}, {"source": "users_quentin_gallois_documents_projects_perso_klozy_klozy_mobile_lib_src_feature_auth_presentation_bloc_auth_bloc_dart", "target": "package_bloc_bloc_dart", "relation": "imports", "confidence": "EXTRACTED", "confidence_score": 1.0, "source_file": "lib/src/feature/auth/presentation/bloc/auth_bloc.dart", "source_location": null, "weight": 1.0}, {"source": "users_quentin_gallois_documents_projects_perso_klozy_klozy_mobile_lib_src_feature_auth_presentation_bloc_auth_bloc_dart", "target": "package_injectable_injectable_dart", "relation": "imports", "confidence": "EXTRACTED", "confidence_score": 1.0, "source_file": "lib/src/feature/auth/presentation/bloc/auth_bloc.dart", "source_location": null, "weight": 1.0}, {"source": "users_quentin_gallois_documents_projects_perso_klozy_klozy_mobile_lib_src_feature_auth_presentation_bloc_auth_bloc_dart", "target": "package_klozy_src_domain_auth_auth_exception_dart", "relation": "imports", "confidence": "EXTRACTED", "confidence_score": 1.0, "source_file": "lib/src/feature/auth/presentation/bloc/auth_bloc.dart", "source_location": null, "weight": 1.0}, {"source": "users_quentin_gallois_documents_projects_perso_klozy_klozy_mobile_lib_src_feature_auth_presentation_bloc_auth_bloc_dart", "target": "package_klozy_src_domain_auth_auth_repository_dart", "relation": "imports", "confidence": "EXTRACTED", "confidence_score": 1.0, "source_file": "lib/src/feature/auth/presentation/bloc/auth_bloc.dart", "source_location": null, "weight": 1.0}, {"source": "users_quentin_gallois_documents_projects_perso_klozy_klozy_mobile_lib_src_feature_auth_presentation_bloc_auth_bloc_dart", "target": "package_klozy_src_domain_auth_entity_auth_user_dart", "relation": "imports", "confidence": "EXTRACTED", "confidence_score": 1.0, "source_file": "lib/src/feature/auth/presentation/bloc/auth_bloc.dart", "source_location": null, "weight": 1.0}, {"source": "users_quentin_gallois_documents_projects_perso_klozy_klozy_mobile_lib_src_feature_auth_presentation_bloc_auth_bloc_dart", "target": "package_klozy_src_domain_me_me_repository_dart", "relation": "imports", "confidence": "EXTRACTED", "confidence_score": 1.0, "source_file": "lib/src/feature/auth/presentation/bloc/auth_bloc.dart", "source_location": null, "weight": 1.0}, {"source": "users_quentin_gallois_documents_projects_perso_klozy_klozy_mobile_lib_src_feature_auth_presentation_bloc_auth_bloc_dart", "target": "package_klozy_src_feature_auth_presentation_bloc_auth_event_dart", "relation": "imports", "confidence": "EXTRACTED", "confidence_score": 1.0, "source_file": "lib/src/feature/auth/presentation/bloc/auth_bloc.dart", "source_location": null, "weight": 1.0}, {"source": "users_quentin_gallois_documents_projects_perso_klozy_klozy_mobile_lib_src_feature_auth_presentation_bloc_auth_bloc_dart", "target": "package_klozy_src_feature_auth_presentation_bloc_auth_state_dart", "relation": "imports", "confidence": "EXTRACTED", "confidence_score": 1.0, "source_file": "lib/src/feature/auth/presentation/bloc/auth_bloc.dart", "source_location": null, "weight": 1.0}, {"source": "users_quentin_gallois_documents_projects_perso_klozy_klozy_mobile_lib_src_feature_auth_presentation_bloc_auth_bloc_dart", "target": "authemailsubmitted", "relation": "references", "confidence": "EXTRACTED", "confidence_score": 1.0, "source_file": "lib/src/feature/auth/presentation/bloc/auth_bloc.dart", "source_location": null, "weight": 1.0, "context": "type_lookup"}, {"source": "users_quentin_gallois_documents_projects_perso_klozy_klozy_mobile_lib_src_feature_auth_presentation_bloc_auth_bloc_dart", "target": "authgooglepressed", "relation": "references", "confidence": "EXTRACTED", "confidence_score": 1.0, "source_file": "lib/src/feature/auth/presentation/bloc/auth_bloc.dart", "source_location": null, "weight": 1.0, "context": "type_lookup"}, {"source": "users_quentin_gallois_documents_projects_perso_klozy_klozy_mobile_lib_src_feature_auth_presentation_bloc_auth_bloc_dart", "target": "authapplepressed", "relation": "references", "confidence": "EXTRACTED", "confidence_score": 1.0, "source_file": "lib/src/feature/auth/presentation/bloc/auth_bloc.dart", "source_location": null, "weight": 1.0, "context": "type_lookup"}, {"source": "users_quentin_gallois_documents_projects_perso_klozy_klozy_mobile_lib_src_feature_auth_presentation_bloc_auth_bloc_dart", "target": "authpasswordresetrequested", "relation": "references", "confidence": "EXTRACTED", "confidence_score": 1.0, "source_file": "lib/src/feature/auth/presentation/bloc/auth_bloc.dart", "source_location": null, "weight": 1.0, "context": "type_lookup"}, {"source": "users_quentin_gallois_documents_projects_perso_klozy_klozy_mobile_lib_src_feature_auth_presentation_bloc_auth_bloc_dart", "target": "authphonestarted", "relation": "references", "confidence": "EXTRACTED", "confidence_score": 1.0, "source_file": "lib/src/feature/auth/presentation/bloc/auth_bloc.dart", "source_location": null, "weight": 1.0, "context": "type_lookup"}, {"source": "users_quentin_gallois_documents_projects_perso_klozy_klozy_mobile_lib_src_feature_auth_presentation_bloc_auth_bloc_dart", "target": "authphonecodesubmitted", "relation": "references", "confidence": "EXTRACTED", "confidence_score": 1.0, "source_file": "lib/src/feature/auth/presentation/bloc/auth_bloc.dart", "source_location": null, "weight": 1.0, "context": "type_lookup"}]}